{
  "openapi": "3.0.1",
  "info": {
    "title": "EducationManagementSystem",
    "description": "",
    "version": "v1"
  },
  "paths": {
    "/api/Account/Login": {
      "post": {
        "tags": [
          "Account"
        ],
        "requestBody": {
          "content": {
            "application/json-patch+json": {
              "schema": {
                "$ref": "#/components/schemas/LoginViewModel"
              }
            },
            "application/json": {
              "schema": {
                "$ref": "#/components/schemas/LoginViewModel"
              }
            },
            "text/json": {
              "schema": {
                "$ref": "#/components/schemas/LoginViewModel"
              }
            },
            "application/*+json": {
              "schema": {
                "$ref": "#/components/schemas/LoginViewModel"
              }
            }
          }
        },
        "responses": {
          "200": {
            "description": "OK"
          }
        }
      }
    },
    "/api/Account/Logout": {
      "post": {
        "tags": [
          "Account"
        ],
        "responses": {
          "200": {
            "description": "OK"
          }
        }
      }
    },
    "/api/Client/add-client": {
      "post": {
        "tags": [
          "Client"
        ],
        "requestBody": {
          "content": {
            "application/json-patch+json": {
              "schema": {
                "$ref": "#/components/schemas/ClientCreateViewModel"
              }
            },
            "application/json": {
              "schema": {
                "$ref": "#/components/schemas/ClientCreateViewModel"
              }
            },
            "text/json": {
              "schema": {
                "$ref": "#/components/schemas/ClientCreateViewModel"
              }
            },
            "application/*+json": {
              "schema": {
                "$ref": "#/components/schemas/ClientCreateViewModel"
              }
            }
          }
        },
        "responses": {
          "200": {
            "description": "OK"
          }
        }
      }
    },
    "/api/Client/get-clients": {
      "get": {
        "tags": [
          "Client"
        ],
        "responses": {
          "200": {
            "description": "OK"
          }
        }
      }
    },
    "/api/Contact/add-contact": {
      "post": {
        "tags": [
          "Contact"
        ],
        "requestBody": {
          "content": {
            "application/json-patch+json": {
              "schema": {
                "$ref": "#/components/schemas/ContactCreateViewModel"
              }
            },
            "application/json": {
              "schema": {
                "$ref": "#/components/schemas/ContactCreateViewModel"
              }
            },
            "text/json": {
              "schema": {
                "$ref": "#/components/schemas/ContactCreateViewModel"
              }
            },
            "application/*+json": {
              "schema": {
                "$ref": "#/components/schemas/ContactCreateViewModel"
              }
            }
          }
        },
        "responses": {
          "200": {
            "description": "OK"
          }
        }
      }
    },
    "/api/Contact/all": {
      "get": {
        "tags": [
          "Contact"
        ],
        "responses": {
          "200": {
            "description": "OK"
          }
        }
      }
    },
    "/api/Contact/by-student/{studentId}": {
      "get": {
        "tags": [
          "Contact"
        ],
        "parameters": [
          {
            "name": "studentId",
            "in": "path",
            "required": true,
            "schema": {
              "type": "string"
            }
          }
        ],
        "responses": {
          "200": {
            "description": "OK"
          }
        }
      }
    },
    "/api/Contact/assign-contact-to-student": {
      "post": {
        "tags": [
          "Contact"
        ],
        "requestBody": {
          "content": {
            "application/json-patch+json": {
              "schema": {
                "$ref": "#/components/schemas/AddContactsToStudentViewModel"
              }
            },
            "application/json": {
              "schema": {
                "$ref": "#/components/schemas/AddContactsToStudentViewModel"
              }
            },
            "text/json": {
              "schema": {
                "$ref": "#/components/schemas/AddContactsToStudentViewModel"
              }
            },
            "application/*+json": {
              "schema": {
                "$ref": "#/components/schemas/AddContactsToStudentViewModel"
              }
            }
          }
        },
        "responses": {
          "200": {
            "description": "OK"
          }
        }
      }
    },
    "/api/Guardians/add-guardian": {
      "post": {
        "tags": [
          "Guardians"
        ],
        "requestBody": {
          "content": {
            "application/json-patch+json": {
              "schema": {
                "$ref": "#/components/schemas/GuardianRequestViewModel"
              }
            },
            "application/json": {
              "schema": {
                "$ref": "#/components/schemas/GuardianRequestViewModel"
              }
            },
            "text/json": {
              "schema": {
                "$ref": "#/components/schemas/GuardianRequestViewModel"
              }
            },
            "application/*+json": {
              "schema": {
                "$ref": "#/components/schemas/GuardianRequestViewModel"
              }
            }
          }
        },
        "responses": {
          "200": {
            "description": "OK"
          }
        }
      }
    },
    "/api/Guardians/update-guardian/{id}": {
      "put": {
        "tags": [
          "Guardians"
        ],
        "parameters": [
          {
            "name": "Guardianid",
            "in": "query",
            "schema": {
              "type": "string"
            }
          },
          {
            "name": "id",
            "in": "path",
            "required": true,
            "schema": {
              "type": "string"
            }
          }
        ],
        "requestBody": {
          "content": {
            "application/json-patch+json": {
              "schema": {
                "$ref": "#/components/schemas/GuardianUpdateViewModel"
              }
            },
            "application/json": {
              "schema": {
                "$ref": "#/components/schemas/GuardianUpdateViewModel"
              }
            },
            "text/json": {
              "schema": {
                "$ref": "#/components/schemas/GuardianUpdateViewModel"
              }
            },
            "application/*+json": {
              "schema": {
                "$ref": "#/components/schemas/GuardianUpdateViewModel"
              }
            }
          }
        },
        "responses": {
          "200": {
            "description": "OK"
          }
        }
      }
    },
    "/api/Guardians/get-all-guardian": {
      "get": {
        "tags": [
          "Guardians"
        ],
        "responses": {
          "200": {
            "description": "OK"
          }
        }
      }
    },
    "/api/Student/add": {
      "post": {
        "tags": [
          "Student"
        ],
        "requestBody": {
          "content": {
            "application/json-patch+json": {
              "schema": {
                "$ref": "#/components/schemas/StudentCreateViewModel"
              }
            },
            "application/json": {
              "schema": {
                "$ref": "#/components/schemas/StudentCreateViewModel"
              }
            },
            "text/json": {
              "schema": {
                "$ref": "#/components/schemas/StudentCreateViewModel"
              }
            },
            "application/*+json": {
              "schema": {
                "$ref": "#/components/schemas/StudentCreateViewModel"
              }
            }
          }
        },
        "responses": {
          "200": {
            "description": "OK"
          }
        }
      }
    },
    "/api/StudentProfile/profile-Add-Update": {
      "post": {
        "tags": [
          "StudentProfile"
        ],
        "requestBody": {
          "content": {
            "application/json-patch+json": {
              "schema": {
                "$ref": "#/components/schemas/StudentProfileViewModel"
              }
            },
            "application/json": {
              "schema": {
                "$ref": "#/components/schemas/StudentProfileViewModel"
              }
            },
            "text/json": {
              "schema": {
                "$ref": "#/components/schemas/StudentProfileViewModel"
              }
            },
            "application/*+json": {
              "schema": {
                "$ref": "#/components/schemas/StudentProfileViewModel"
              }
            }
          }
        },
        "responses": {
          "200": {
            "description": "OK"
          }
        }
      }
    },
    "/api/StudentProfile/{studentId}": {
      "get": {
        "tags": [
          "StudentProfile"
        ],
        "parameters": [
          {
            "name": "studentId",
            "in": "path",
            "required": true,
            "schema": {
              "type": "string"
            }
          }
        ],
        "responses": {
          "200": {
            "description": "OK"
          }
        }
      }
    },
    "/api/Venue/add-venue": {
      "post": {
        "tags": [
          "Venue"
        ],
        "requestBody": {
          "content": {
            "application/json-patch+json": {
              "schema": {
                "$ref": "#/components/schemas/VenueRequestViewModel"
              }
            },
            "application/json": {
              "schema": {
                "$ref": "#/components/schemas/VenueRequestViewModel"
              }
            },
            "text/json": {
              "schema": {
                "$ref": "#/components/schemas/VenueRequestViewModel"
              }
            },
            "application/*+json": {
              "schema": {
                "$ref": "#/components/schemas/VenueRequestViewModel"
              }
            }
          }
        },
        "responses": {
          "200": {
            "description": "OK"
          }
        }
      }
    },
    "/api/Venue/update-venue-{id}": {
      "put": {
        "tags": [
          "Venue"
        ],
        "parameters": [
          {
            "name": "id",
            "in": "path",
            "required": true,
            "schema": {
              "type": "string",
              "format": "uuid"
            }
          }
        ],
        "requestBody": {
          "content": {
            "application/json-patch+json": {
              "schema": {
                "$ref": "#/components/schemas/VenueRequestViewModel"
              }
            },
            "application/json": {
              "schema": {
                "$ref": "#/components/schemas/VenueRequestViewModel"
              }
            },
            "text/json": {
              "schema": {
                "$ref": "#/components/schemas/VenueRequestViewModel"
              }
            },
            "application/*+json": {
              "schema": {
                "$ref": "#/components/schemas/VenueRequestViewModel"
              }
            }
          }
        },
        "responses": {
          "200": {
            "description": "OK"
          }
        }
      }
    },
    "/api/Venue/all-venues": {
      "get": {
        "tags": [
          "Venue"
        ],
        "parameters": [
          {
            "name": "searchTerm",
            "in": "query",
            "schema": {
              "type": "string"
            }
          }
        ],
        "responses": {
          "200": {
            "description": "OK"
          }
        }
      }
    }
  },
  "components": {
    "schemas": {
      "AddContactsToStudentViewModel": {
        "type": "object",
        "properties": {
          "studentId": {
            "type": "string",
            "nullable": true
          },
          "contacts": {
            "type": "array",
            "items": {
              "$ref": "#/components/schemas/ContactSelection"
            },
            "nullable": true
          }
        },
        "additionalProperties": false
      },
      "ClientCreateViewModel": {
        "type": "object",
        "properties": {
          "firstName": {
            "type": "string",
            "nullable": true
          },
          "lastName": {
            "type": "string",
            "nullable": true
          },
          "mobile": {
            "type": "string",
            "nullable": true
          },
          "email": {
            "type": "string",
            "format": "email",
            "nullable": true
          },
          "building": {
            "type": "integer",
            "format": "int32",
            "nullable": true
          },
          "street": {
            "type": "string",
            "nullable": true
          },
          "addressLine2": {
            "type": "string",
            "nullable": true
          },
          "town": {
            "type": "string",
            "nullable": true
          },
          "county": {
            "type": "string",
            "nullable": true
          },
          "postCode": {
            "type": "string",
            "nullable": true
          },
          "country": {
            "type": "string",
            "nullable": true
          },
          "contactTelephone": {
            "type": "string",
            "nullable": true
          },
          "contactEmail": {
            "type": "string",
            "format": "email",
            "nullable": true
          },
          "status": {
            "type": "boolean"
          }
        },
        "additionalProperties": false
      },
      "ContactCreateViewModel": {
        "required": [
          "contactName",
          "mobile"
        ],
        "type": "object",
        "properties": {
          "contactName": {
            "minLength": 1,
            "type": "string"
          },
          "mobile": {
            "minLength": 1,
            "type": "string"
          },
          "email": {
            "type": "string",
            "format": "email",
            "nullable": true
          },
          "jobTitle": {
            "type": "string",
            "nullable": true
          },
          "report": {
            "type": "string",
            "nullable": true
          },
          "trigger": {
            "$ref": "#/components/schemas/ReportTrigger"
          },
          "clientId": {
            "type": "string",
            "nullable": true
          }
        },
        "additionalProperties": false
      },
      "ContactSelection": {
        "type": "object",
        "properties": {
          "contactId": {
            "type": "integer",
            "format": "int32"
          },
          "isSelected": {
            "type": "boolean"
          }
        },
        "additionalProperties": false
      },
      "GuardianRequestViewModel": {
        "type": "object",
        "properties": {
          "firstName": {
            "type": "string",
            "nullable": true
          },
          "lastName": {
            "type": "string",
            "nullable": true
          },
          "mobile": {
            "type": "string",
            "nullable": true
          },
          "email": {
            "type": "string",
            "format": "email",
            "nullable": true
          },
          "building": {
            "type": "integer",
            "format": "int32",
            "nullable": true
          },
          "street": {
            "type": "string",
            "nullable": true
          },
          "addressLine2": {
            "type": "string",
            "nullable": true
          },
          "town": {
            "type": "string",
            "nullable": true
          },
          "county": {
            "type": "string",
            "nullable": true
          },
          "postCode": {
            "type": "string",
            "nullable": true
          },
          "country": {
            "type": "string",
            "nullable": true
          },
          "profile": {
            "type": "string",
            "nullable": true
          },
          "guardian2FirstName": {
            "type": "string",
            "nullable": true
          },
          "guardian2LastName": {
            "type": "string",
            "nullable": true
          },
          "guardian2Mobile": {
            "type": "string",
            "nullable": true
          },
          "guardian2Email": {
            "type": "string",
            "format": "email",
            "nullable": true
          },
          "guardian2Building": {
            "type": "integer",
            "format": "int32"
          },
          "guardian2Street": {
            "type": "string",
            "nullable": true
          },
          "guardian2AddressLine2": {
            "type": "string",
            "nullable": true
          },
          "guardian2Town": {
            "type": "string",
            "nullable": true
          },
          "guardian2County": {
            "type": "string",
            "nullable": true
          },
          "guardian2PostCode": {
            "type": "string",
            "nullable": true
          },
          "guardian2Country": {
            "type": "string",
            "nullable": true
          },
          "guardian2Profile": {
            "type": "string",
            "nullable": true
          },
          "safeguardingLeadContact": {
            "type": "string",
            "nullable": true
          },
          "appStatus": {
            "type": "boolean"
          }
        },
        "additionalProperties": false
      },
      "GuardianUpdateViewModel": {
        "type": "object",
        "properties": {
          "firstName": {
            "type": "string",
            "nullable": true
          },
          "lastName": {
            "type": "string",
            "nullable": true
          },
          "mobile": {
            "type": "string",
            "nullable": true
          },
          "email": {
            "type": "string",
            "nullable": true
          },
          "building": {
            "type": "integer",
            "format": "int32",
            "nullable": true
          },
          "street": {
            "type": "string",
            "nullable": true
          },
          "addressLine2": {
            "type": "string",
            "nullable": true
          },
          "town": {
            "type": "string",
            "nullable": true
          },
          "county": {
            "type": "string",
            "nullable": true
          },
          "postCode": {
            "type": "string",
            "nullable": true
          },
          "country": {
            "type": "string",
            "nullable": true
          },
          "profile": {
            "type": "string",
            "nullable": true
          },
          "guardian2FirstName": {
            "type": "string",
            "nullable": true
          },
          "guardian2LastName": {
            "type": "string",
            "nullable": true
          },
          "guardian2Mobile": {
            "type": "string",
            "nullable": true
          },
          "guardian2Email": {
            "type": "string",
            "nullable": true
          },
          "guardian2Building": {
            "type": "integer",
            "format": "int32",
            "nullable": true
          },
          "guardian2Street": {
            "type": "string",
            "nullable": true
          },
          "guardian2AddressLine2": {
            "type": "string",
            "nullable": true
          },
          "guardian2Town": {
            "type": "string",
            "nullable": true
          },
          "guardian2County": {
            "type": "string",
            "nullable": true
          },
          "guardian2PostCode": {
            "type": "string",
            "nullable": true
          },
          "guardian2Country": {
            "type": "string",
            "nullable": true
          },
          "guardian2Profile": {
            "type": "string",
            "nullable": true
          },
          "safeguardingLeadContact": {
            "type": "string",
            "nullable": true
          },
          "appStatus": {
            "type": "boolean",
            "nullable": true
          }
        },
        "additionalProperties": false
      },
      "LoginViewModel": {
        "required": [
          "email",
          "password"
        ],
        "type": "object",
        "properties": {
          "email": {
            "minLength": 1,
            "type": "string",
            "format": "email"
          },
          "password": {
            "minLength": 1,
            "type": "string",
            "format": "password"
          },
          "rememberMe": {
            "type": "boolean"
          }
        },
        "additionalProperties": false
      },
      "ReportTrigger": {
        "enum": [
          0,
          1,
          2
        ],
        "type": "integer",
        "format": "int32"
      },
      "StudentCreateViewModel": {
        "type": "object",
        "properties": {
          "firstName": {
            "type": "string",
            "nullable": true
          },
          "lastName": {
            "type": "string",
            "nullable": true
          },
          "password": {
            "type": "string",
            "nullable": true
          },
          "preferredName": {
            "type": "string",
            "nullable": true
          },
          "isMale": {
            "type": "boolean"
          },
          "dateOfBirth": {
            "type": "string",
            "format": "date-time"
          },
          "building": {
            "type": "integer",
            "format": "int32",
            "nullable": true
          },
          "street": {
            "type": "string",
            "nullable": true
          },
          "addressLine2": {
            "type": "string",
            "nullable": true
          },
          "town": {
            "type": "string",
            "nullable": true
          },
          "county": {
            "type": "string",
            "nullable": true
          },
          "postCode": {
            "type": "string",
            "nullable": true
          },
          "country": {
            "type": "string",
            "nullable": true
          },
          "clientId": {
            "type": "string",
            "nullable": true
          }
        },
        "additionalProperties": false
      },
      "StudentProfileViewModel": {
        "type": "object",
        "properties": {
          "studentId": {
            "type": "string",
            "nullable": true
          },
          "school": {
            "type": "string",
            "nullable": true
          },
          "schoolYear": {
            "type": "string",
            "nullable": true
          },
          "currentLevel": {
            "type": "string",
            "nullable": true
          },
          "summary": {
            "type": "string",
            "nullable": true
          },
          "sen": {
            "type": "string",
            "nullable": true
          },
          "learningObjectives": {
            "type": "string",
            "nullable": true
          }
        },
        "additionalProperties": false
      },
      "VenueRequestViewModel": {
        "type": "object",
        "properties": {
          "venueName": {
            "type": "string",
            "nullable": true
          },
          "postCode": {
            "type": "string",
            "nullable": true
          },
          "building": {
            "type": "integer",
            "format": "int32"
          },
          "street": {
            "type": "string",
            "nullable": true
          },
          "addressLine2": {
            "type": "string",
            "nullable": true
          },
          "town": {
            "type": "string",
            "nullable": true
          },
          "county": {
            "type": "string",
            "nullable": true
          },
          "country": {
            "type": "string",
            "nullable": true
          },
          "longandLat": {
            "type": "string",
            "nullable": true
          }
        },
        "additionalProperties": false
      }
    },
    "securitySchemes": {
      "Bearer": {
        "type": "http",
        "description": "Enter 'Bearer' [space] and then your valid token in the text input below.\r\n\r\nExample: \"eyJhbGciOiJIUzI1NiIsInR5cCI6IkpXVCJ9\"",
        "scheme": "Bearer",
        "bearerFormat": "JWT"
      }
    }
  },
  "security": [
    {
      "Bearer": [ ]
    }
  ]
}